pywombat/__init__.py
pywombat/cli.py
pywombat-1.0.1.dist-info/METADATA
pywombat-1.0.1.dist-info/WHEEL
pywombat-1.0.1.dist-info/entry_points.txt
pywombat-1.0.1.dist-info/RECORD
