Metadata-Version: 2.4
Name: pywombat
Version: 1.0.1
Summary: A CLI tool for processing and filtering bcftools tabulated TSV files with pedigree support
Project-URL: Homepage, https://github.com/bourgeron-lab/pywombat
Project-URL: Repository, https://github.com/bourgeron-lab/pywombat
Project-URL: Issues, https://github.com/bourgeron-lab/pywombat/issues
Author-email: Freddy Cliquet <fcliquet@pasteur.fr>
License: MIT
Keywords: bioinformatics,genomics,pedigree,variant-calling,vcf
Classifier: Development Status :: 5 - Production/Stable
Classifier: Intended Audience :: Science/Research
Classifier: Programming Language :: Python :: 3
Classifier: Programming Language :: Python :: 3.12
Classifier: Topic :: Scientific/Engineering :: Bio-Informatics
Requires-Python: >=3.12
Requires-Dist: click>=8.1.0
Requires-Dist: polars>=0.19.0
Requires-Dist: pyyaml>=6.0
Requires-Dist: tqdm>=4.67.1
